cozy/__init__.py
cozy/__main__.py
cozy/analysis.py
cozy/claripy_ext.py
cozy/concrete.py
cozy/constants.py
cozy/directive.py
cozy/execution_graph.py
cozy/functools_ext.py
cozy/log.py
cozy/primitives.py
cozy/project.py
cozy/server.py
cozy/session.py
cozy/side_effect.py
cozy/stubs.py
cozy/terminal_state.py
cozy/types.py
cozy/underconstrained.py
cozy/concolic/__init__.py
cozy/concolic/exploration.py
cozy/concolic/heuristics.py
cozy/concolic/session.py
cozy/hooks/__init__.py
cozy/hooks/strlen.py
cozy/hooks/strncmp.py
cozy/hooks/strtok_r.py
cozy-viz/README.md
cozy-viz/bundle.js
cozy-viz/bundler.mjs
cozy-viz/cozy-viz.js
cozy-viz/flake.lock
cozy-viz/flake.nix
cozy-viz/index.css
cozy-viz/index.html
cozy-viz/package-lock.json
cozy-viz/package.json
cozy-viz/report.css
cozy-viz/components/actionDifference.js
cozy-viz/components/app.js
cozy-viz/components/assemblyDifference.js
cozy-viz/components/concretionSelector.js
cozy-viz/components/concretions.js
cozy-viz/components/diffPanel.js
cozy-viz/components/hunk.js
cozy-viz/components/layoutMenu.js
cozy-viz/components/lineDiffView.js
cozy-viz/components/memoryDifference.js
cozy-viz/components/menu.js
cozy-viz/components/menuBar.js
cozy-viz/components/pruneMenu.js
cozy-viz/components/registerDifference.js
cozy-viz/components/report.js
cozy-viz/components/searchInput.js
cozy-viz/components/searchMenu.js
cozy-viz/components/sideEffectDifference.js
cozy-viz/components/tooltip.js
cozy-viz/components/viewMenu.js
cozy-viz/data/colors.js
cozy-viz/data/cozy-data.js
cozy-viz/data/layouts.js
cozy-viz/util/checkedMixin.js
cozy-viz/util/constraints.js
cozy-viz/util/focusMixin.js
cozy-viz/util/graph-tidy.js
cozy-viz/util/graphStyle.js
cozy-viz/util/segmentation.js
cozy-viz/util/segmentationMixin.js
cozy_re-1.5.3.dist-info/METADATA
cozy_re-1.5.3.dist-info/WHEEL
cozy_re-1.5.3.dist-info/licenses/LICENSE
cozy_re-1.5.3.dist-info/licenses/LICENSE_USG
cozy_re-1.5.3.dist-info/RECORD
