Metadata-Version: 2.4
Name: cozy-re
Version: 1.5.3
Summary: The Cozy Comparative Symbolic Evaluation Engine
Project-URL: Homepage, https://github.com/draperlaboratory/cozy
Project-URL: Bug Tracker, https://github.com/draperlaboratory/cozy/issues
Author-email: Caleb Helbling <chelbling@draper.com>, Graham Leach-Krouse <gleach-krouse@draper.com>
License-File: LICENSE
License-File: LICENSE_USG
Classifier: License :: OSI Approved :: MIT License
Classifier: Operating System :: OS Independent
Classifier: Programming Language :: Python :: 3
Requires-Python: >=3.10
Requires-Dist: angr==9.2.130
Requires-Dist: claripy==9.2.130
Requires-Dist: networkx==3.3
Requires-Dist: portion==2.4.2
Requires-Dist: textual==0.86.1
